cbutil/__init__.py
cbutil/class_creator/__init__.py
cbutil/class_creator/signset_creator.py
cbutil/container/__init__.py
cbutil/container/signed_set.py
cbutil/coro/__init__.py
cbutil/coro/coro_exec.py
cbutil/coro/coro_queue.py
cbutil/tool/__init__.py
cbutil/util/__init__.py
cbutil/util/adaptor.py
cbutil/util/iterutil.py
cbutil/util/path.py
cbutil/util/pbar.py
cbutil/util/printutil.py
cbutil/util/random.py
cbutil/util/url.py
cbutil/util/util.py
cbutil-1.2.7.dist-info/LICENSE
cbutil-1.2.7.dist-info/METADATA
cbutil-1.2.7.dist-info/WHEEL
cbutil-1.2.7.dist-info/top_level.txt
cbutil-1.2.7.dist-info/RECORD
