Metadata-Version: 2.1
Name: cbutil
Version: 1.2.7
Summary: Utility Library
Home-page: https://github.com/happyxianyu/cbutil-python
Author: happyxianyu
Author-email: happyxianyu623@outlook.com
License: Apache License 2.0
Platform: UNKNOWN
Requires-Python: >=3.8
Requires-Dist: base58
Requires-Dist: more-itertools
